LICENSE
MANIFEST.in
README.md
config.ini
setup.cfg
setup.py
metrics_collector/__init__.py
metrics_collector/client.py
metrics_collector/config.py
metrics_collector/main.py
metrics_collector/manager.py
metrics_collector/utils.py
metrics_collector.egg-info/PKG-INFO
metrics_collector.egg-info/SOURCES.txt
metrics_collector.egg-info/dependency_links.txt
metrics_collector.egg-info/entry_points.txt
metrics_collector.egg-info/requires.txt
metrics_collector.egg-info/top_level.txt
metrics_collector/collectors/__init__.py
metrics_collector/collectors/base.py
metrics_collector/collectors/cpu.py
metrics_collector/collectors/disk.py
metrics_collector/collectors/load.py
metrics_collector/collectors/memory.py
metrics_collector/collectors/net.py
metrics_collector/common/__init__.py
metrics_collector/common/daemon.py
metrics_collector/common/ipc.py
metrics_collector/common/logger.py
metrics_collector/common/loggerconfig.py
metrics_collector/common/loggingmp.py
metrics_collector/common/osutils.py