Metadata-Version: 1.0
Name: metrics-collector
Version: 0.2.0
Summary: System monitoring daemon that logs to InfluxDB
Home-page: http://git.garena.com/core-services/metrics_collector
Author: Jia Mengchi
Author-email: jiam@garena.com
License: UNKNOWN
Platform: UNKNOWN
